{
  "document": {
    "id": "LAWIM-H13-WORKFLOW-EXT-V1",
    "title": "Workflow Extension Catalog — Heritage Gold → LAWIM_V2",
    "status": "CANONICAL",
    "date": "2026-07-15",
    "description": "Complete machine-readable catalog of all workflow extensions from Heritage Gold → LAWIM_V2, including all state machines, transitions, guards, triggers, actions, SLA, NBA rules, events, and failure policies for 21 workflows",
    "sources": [
      "WORKFLOW_STATE_CROSSWALK.md",
      "required_extensions.json (workflows section)",
      "LAWIM_UNIFIED_DOMAIN_MODEL.md §5 (Dossier), §6 (Matching), §7 (Visit), §8 (Negotiation), §9 (Transaction), §10 (CRM), §14 (Document), §3 (Property)"
    ],
    "total_extensions": 21,
    "by_category": {
      "workflows_from_required_extensions": 14,
      "additional_workflows_from_domain_model": 7,
      "total_states": 191,
      "total_transitions": 280
    }
  },
  "workflows": [
    {
      "extension_id": "EXT-WF-001",
      "source_concept": "Matching Lifecycle (10 states)",
      "source_document": "WORKFLOW_STATE_CROSSWALK.md / WORKFLOW_03 (Gold)",
      "source_rule_ids": ["WORKFLOW_03", "MATCHING_MODEL.md"],
      "current_target": "No existing entity",
      "current_limitation": "No matching engine or state machine exists in V2",
      "extension_category": "workflow_generic_state_machine",
      "proposed_domain": "Domain 6: Matching Engine",
      "proposed_entity": "Match",
      "proposed_structure": "CREATE_NEW_GENERIC_STATE_MACHINE — Implement Match entity with 10-state lifecycle and 5-dimension scoring engine",
      "decision": "CREATE_NEW_GENERIC_STATE_MACHINE",
      "workflow_id": "matching_lifecycle",
      "entity_type": "Match",
      "initial_state": "created",
      "states": ["created", "scored", "proposed", "demandeur_review", "holder_review", "double_consent_obtained", "mise_en_relation_established", "active", "expired", "archived"],
      "terminal_states": ["mise_en_relation_established", "expired", "archived"],
      "transitions": [
        {"from": "created", "to": "scored", "trigger": "score_calculated", "guard": "all_scoring_dimensions_complete", "action": "calculate_score"},
        {"from": "scored", "to": "proposed", "trigger": "auto_propose", "guard": "score_ge_60_and_rank_top_10", "action": "create_proposal"},
        {"from": "scored", "to": "archived", "trigger": "low_score", "guard": "score_lt_60_and_no_expansion", "action": "archive_match"},
        {"from": "proposed", "to": "demandeur_review", "trigger": "demandeur_notified", "guard": "proposal_sent", "action": "start_decision_timer"},
        {"from": "demandeur_review", "to": "holder_review", "trigger": "demandeur_interested", "guard": "consent_given", "action": "notify_holder"},
        {"from": "demandeur_review", "to": "rematched", "trigger": "demandeur_not_interested", "guard": "refusal_received", "action": "exclude_property_and_recalculate"},
        {"from": "demandeur_review", "to": "expired", "trigger": "timer_expired", "guard": "decision_deadline_passed", "action": "mark_expired"},
        {"from": "holder_review", "to": "double_consent_obtained", "trigger": "holder_favorable", "guard": "consent_given", "action": "record_consent"},
        {"from": "holder_review", "to": "rematched", "trigger": "holder_refused", "guard": "refusal_received", "action": "exclude_property_and_recalculate"},
        {"from": "double_consent_obtained", "to": "mise_en_relation_established", "trigger": "contact_created", "guard": "double_consent_confirmed", "action": "create_contact"},
        {"from": "mise_en_relation_established", "to": "active", "trigger": "visit_initiated", "guard": "visit_scheduled", "action": "update_match_status"},
        {"from": "active", "to": "expired", "trigger": "match_inactivity", "guard": "30d_no_activity", "action": "recalculate_score"},
        {"from": "active", "to": "archived", "trigger": "match_completed", "guard": "transaction_completed_or_cancelled", "action": "archive_match"},
        {"from": "expired", "to": "scored", "trigger": "recalculate", "guard": "dossier_or_property_updated", "action": "recalculate_score"}
      ],
      "guards": [
        {"name": "all_scoring_dimensions_complete", "condition": "All 5 scoring dimensions have been computed", "scope": "match"},
        {"name": "score_ge_60", "condition": "Overall composite score >= 60", "scope": "match"},
        {"name": "rank_in_top_10", "condition": "Match is among top 10 for this project", "scope": "project"},
        {"name": "consent_given", "condition": "User has explicitly consented", "scope": "demandeur_or_holder"},
        {"name": "decision_deadline_passed", "condition": "72h elapsed without response", "scope": "match"},
        {"name": "30d_no_activity", "condition": "30 days without activity", "scope": "match"},
        {"name": "double_consent_confirmed", "condition": "Both demandeur and holder consented", "scope": "match"}
      ],
      "triggers": [
        {"name": "score_calculated", "source": "System (matching engine)", "event": "match.score_calculated"},
        {"name": "auto_propose", "source": "System (matching engine)", "event": "match.proposed"},
        {"name": "demandeur_interested", "source": "Demandeur action", "event": "match.demandeur_accepted"},
        {"name": "holder_favorable", "source": "Holder action", "event": "match.holder_accepted"},
        {"name": "holder_refused", "source": "Holder action", "event": "match.holder_rejected"},
        {"name": "timer_expired", "source": "System (cron)", "event": "match.decision_expired"},
        {"name": "match_inactivity", "source": "System (cron)", "event": "match.inactivity_detected"},
        {"name": "recalculate", "source": "System (event)", "event": "match.recalculate_requested"}
      ],
      "actions": [
        {"name": "calculate_score", "description": "Compute composite score from 5 dimensions", "async": true},
        {"name": "assign_compatibility_level", "description": "Map score to Excellent/Good/Average/Low", "async": false},
        {"name": "create_proposal", "description": "Generate match proposal with score breakdown", "async": false},
        {"name": "notify_demandeur", "description": "Send match proposal to demandeur", "async": true},
        {"name": "notify_holder", "description": "Inform holder of demandeur interest", "async": true},
        {"name": "start_decision_timer", "description": "Set 72h deadline for decision", "async": true},
        {"name": "record_consent", "description": "Log consent timestamp and actor", "async": false},
        {"name": "send_reminder", "description": "Send silence reminder (1/2/3/last)", "async": true},
        {"name": "exclude_property", "description": "Remove property from current match pool", "async": false},
        {"name": "archive_match", "description": "Move match to archived state", "async": false}
      ],
      "SLA": [
        {"state": "demandeur_review", "max_duration": "72h", "escalation": "Reminder at 24h, 48h, auto-expire"},
        {"state": "holder_review", "max_duration": "72h", "escalation": "Reminder at 24h, 48h, 72h"},
        {"state": "active", "max_duration": "30d inactivity", "escalation": "Recalculate score, notify both parties"}
      ],
      "NBA_rules": [
        {"state": "scored", "nba": "Review match proposal or expand search criteria"},
        {"state": "demandeur_review", "nba": "Respond to match proposal"},
        {"state": "holder_review", "nba": "Awaiting holder response"},
        {"state": "double_consent_obtained", "nba": "Establish contact between parties"},
        {"state": "mise_en_relation_established", "nba": "Schedule a visit"},
        {"state": "expired", "nba": "Request rematch or update dossier criteria"}
      ],
      "events": [
        "match.created (project_id, property_id, initial_score)",
        "match.score_calculated (match_id, score_dimensions, composite_score, compatibility_level)",
        "match.proposed (match_id, rank, score, proposal_method)",
        "match.demandeur_accepted (match_id, demandeur_id, decision_timestamp)",
        "match.demandeur_rejected (match_id, demandeur_id, reason)",
        "match.holder_accepted (match_id, holder_id, decision_timestamp)",
        "match.holder_rejected (match_id, holder_id, reason)",
        "match.expired (match_id, expiry_reason)",
        "match.rematched (match_id, old_property_id, new_property_id, rematch_count)",
        "match.archived (match_id, archive_reason)",
        "match.contact_established (match_id, contact_id)"
      ],
      "failure_policy": {
        "scoring_failure": "Retry (max 3), log error, transition to failed state",
        "notification_failure": "Queue retry (max 5), fallback to in-app notification",
        "reminder_failure": "Cron job health check, manual trigger available",
        "database_transaction_conflict": "Atomic transaction with rollback, retry on conflict",
        "match_proposal_expiry": "Auto-transition to expired, notify demandeur"
      },
      "required_fields": [
        "Match.id: UUID",
        "Match.project_id: UUID (FK → Project)",
        "Match.property_id: UUID (FK → Property)",
        "Match.agent_id: UUID? (FK → User)",
        "Match.overall_score: Float (0-100)",
        "Match.compatibility_level: Enum (excellent | good | average | low)",
        "Match.rank: Int",
        "Match.is_active: Boolean",
        "Match.is_proposed: Boolean",
        "Match.demandeur_decision: Enum? (pending | interested | not_interested)",
        "Match.holder_decision: Enum? (pending | favorable | refused)",
        "Match.rematch_count: Int (default 0)",
        "Match.state: Enum (10 states)",
        "Match.created_at: DateTime",
        "Match.expires_at: DateTime"
      ],
      "required_relations": [
        "Match.project_id → Project",
        "Match.property_id → Property",
        "Match.agent_id → User (agent)"
      ],
      "required_events": [
        "match.created (payload: {project_id, property_id, initial_score})",
        "match.score_calculated (payload: {match_id, score_dimensions[], composite_score, compatibility_level})",
        "match.proposed (payload: {match_id, rank, score, proposal_method})",
        "match.demandeur_accepted (payload: {match_id, demandeur_id, decision_timestamp})",
        "match.holder_accepted (payload: {match_id, holder_id, decision_timestamp})",
        "match.expired (payload: {match_id, expiry_reason})",
        "match.rematched (payload: {match_id, old_property_id, new_property_id, rematch_count})",
        "match.archived (payload: {match_id, archive_reason})"
      ],
      "required_permissions": [
        "USER (demandeur): view own matches, accept/reject",
        "USER (holder): view matches for own properties, accept/reject",
        "AGENT: view matches for assigned properties",
        "ADMIN: view all matches, trigger rematch"
      ],
      "required_states": [
        "Match.state ∈ {created, scored, proposed, demandeur_review, holder_review, double_consent_obtained, mise_en_relation_established, active, expired, archived}"
      ],
      "H0.5_matrices_impacted": ["scoring_dimensions", "geographic_scoring", "compatibility_levels", "boost_penalty_rules"],
      "implementation_priority": "P1",
      "implementation_wave": "Phase 1 — Core Business",
      "human_decision_required": true,
      "human_decision_question": "Matching algorithm design: rule-based (Gold) or ML-enhanced",
      "status": "APPROVED"
    },
    {
      "extension_id": "EXT-WF-002",
      "source_concept": "Mise en Relation / Contact Lifecycle (6 states)",
      "source_document": "WORKFLOW_STATE_CROSSWALK.md / WORKFLOW_04 (Gold)",
      "source_rule_ids": ["WORKFLOW_04"],
      "current_target": "No existing entity",
      "current_limitation": "V2 has conversation model but no contact workflow, no double consent, no holder decision tracking",
      "extension_category": "workflow_specialized",
      "proposed_domain": "Domain 5: Dossier/Project Model (contact sub-workflow)",
      "proposed_entity": "Contact",
      "proposed_structure": "CREATE_SPECIALIZED_WORKFLOW — Implement Contact entity with 6-state lifecycle; enforce double consent; add holder silence escalation with 3-tier reminder system",
      "decision": "CREATE_SPECIALIZED_WORKFLOW",
      "workflow_id": "mise_en_relation",
      "entity_type": "Contact",
      "initial_state": "created",
      "states": ["created", "demandeur_interested", "holder_contacted", "holder_favorable", "consent_obtained", "established", "refused", "expired"],
      "terminal_states": ["established", "refused", "expired"],
      "transitions": [
        {"from": "created", "to": "demandeur_interested", "trigger": "demandeur_consents", "guard": "match_proposed", "action": "record_demandeur_consent_and_notify_holder"},
        {"from": "created", "to": "expired", "trigger": "no_demandeur_action", "guard": "7d_no_response", "action": "cleanup_contact"},
        {"from": "demandeur_interested", "to": "holder_contacted", "trigger": "holder_notified", "guard": "demandeur_consent_confirmed", "action": "send_holder_notification_and_start_timer"},
        {"from": "holder_contacted", "to": "holder_favorable", "trigger": "holder_consents", "guard": "holder_consent_given", "action": "record_holder_consent"},
        {"from": "holder_contacted", "to": "refused", "trigger": "holder_refuses", "guard": "holder_rejects", "action": "notify_demandeur_and_offer_rematch"},
        {"from": "holder_contacted", "to": "expired", "trigger": "holder_silence", "guard": "72h_no_response", "action": "send_reminders_and_escalate"},
        {"from": "holder_favorable", "to": "consent_obtained", "trigger": "double_consent_verified", "guard": "both_consented", "action": "verify_consent_pair"},
        {"from": "consent_obtained", "to": "established", "trigger": "contact_activated", "guard": "consent_valid", "action": "activate_contact_and_reveal_coordinates"},
        {"from": "established", "to": "archived", "trigger": "contact_concluded", "guard": "transaction_or_closure", "action": "archive_contact"}
      ],
      "guards": [
        {"name": "match_proposed", "condition": "Match exists and has been proposed to demandeur"},
        {"name": "7d_no_response", "condition": "Demandeur did not respond within 7 days"},
        {"name": "demandeur_consent_confirmed", "condition": "Demandeur consent has been recorded"},
        {"name": "holder_consent_given", "condition": "Holder has explicitly consented"},
        {"name": "holder_rejects", "condition": "Holder explicitly refuses contact"},
        {"name": "72h_no_response", "condition": "No response from holder after 72h"},
        {"name": "both_consented", "condition": "Both demandeur and holder have given consent"},
        {"name": "consent_valid", "condition": "No consent withdrawal within validity period"}
      ],
      "triggers": [
        {"name": "demandeur_consents", "source": "Demandeur action (UI/chat)"},
        {"name": "no_demandeur_action", "source": "System (cron)"},
        {"name": "holder_consents", "source": "Holder action"},
        {"name": "holder_refuses", "source": "Holder action"},
        {"name": "holder_silence", "source": "System (cron, after 72h)"},
        {"name": "double_consent_verified", "source": "System (consent pair validation)"},
        {"name": "contact_activated", "source": "System (activation check)"}
      ],
      "actions": [
        {"name": "record_demandeur_consent", "description": "Log demandeur consent with timestamp", "async": false},
        {"name": "notify_holder", "description": "Send notification to holder", "async": true},
        {"name": "send_holder_notification", "description": "Send structured contact request", "async": true},
        {"name": "start_holder_timer", "description": "Initialize 72h holder response timer", "async": true},
        {"name": "record_holder_consent", "description": "Log holder consent with timestamp", "async": false},
        {"name": "notify_demandeur", "description": "Inform demandeur of holder refusal", "async": true},
        {"name": "send_reminder", "description": "Send silence reminder (1 at 24h, 2 at 48h, 3 at 72h)", "async": true},
        {"name": "verify_consent_pair", "description": "Confirm both consents are valid", "async": false},
        {"name": "activate_contact", "description": "Enable communication channel between parties", "async": true},
        {"name": "reveal_coordinates", "description": "Reveal contact details if paid", "async": false}
      ],
      "SLA": [
        {"state": "created", "max_duration": "7d", "escalation": "Auto-expire if demandeur does not consent"},
        {"state": "holder_contacted", "max_duration": "72h", "escalation": "Reminder 1 (24h), 2 (48h), 3 (72h), Last Reminder, then expire"},
        {"state": "established", "max_duration": "90d inactivity", "escalation": "Re-assess match quality"}
      ],
      "NBA_rules": [
        {"state": "created", "nba": "Review match and express interest"},
        {"state": "demandeur_interested", "nba": "Awaiting holder response"},
        {"state": "holder_contacted", "nba": "Respond to contact request (holder)"},
        {"state": "holder_favorable", "nba": "Complete contact establishment"},
        {"state": "consent_obtained", "nba": "Contact is now active — start conversation"},
        {"state": "established", "nba": "Schedule a visit or send a message"},
        {"state": "refused", "nba": "View alternative matches"},
        {"state": "expired", "nba": "Rematch with new property"}
      ],
      "events": [
        "contact.created (match_id, demandeur_id, holder_id, property_id)",
        "contact.demandeur_consented (contact_id, demandeur_id, timestamp)",
        "contact.holder_consented (contact_id, holder_id, timestamp)",
        "contact.holder_refused (contact_id, holder_id, reason)",
        "contact.holder_silence_reminder (contact_id, reminder_number, timestamp)",
        "contact.consent_obtained (contact_id, demandeur_consent_at, holder_consent_at)",
        "contact.established (contact_id, activated_at, channel)",
        "contact.refused (contact_id, refused_by, reason)",
        "contact.expired (contact_id, expiry_reason)",
        "contact.archived (contact_id, archive_reason)"
      ],
      "failure_policy": {
        "notification_failure": "Retry (max 5), escalate to agent, log",
        "holder_silence": "After reminders, auto-expire, offer rematch",
        "consent_withdrawal": "If either party withdraws before establishment, cancel contact",
        "duplicate_contact_creation": "Check existing active contact before creation"
      },
      "required_fields": [
        "Contact.id: UUID",
        "Contact.match_id: UUID (FK → Match)",
        "Contact.demandeur_id: UUID (FK → User)",
        "Contact.holder_id: UUID (FK → User)",
        "Contact.property_id: UUID (FK → Property)",
        "Contact.state: Enum (8 states)",
        "Contact.demandeur_consented_at: DateTime?",
        "Contact.holder_consented_at: DateTime?",
        "Contact.consent_obtained_at: DateTime?",
        "Contact.established_at: DateTime?",
        "Contact.expires_at: DateTime?"
      ],
      "required_relations": [
        "Contact.match_id → Match",
        "Contact.demandeur_id → User",
        "Contact.holder_id → User",
        "Contact.property_id → Property"
      ],
      "required_events": [
        "contact.created (payload: {match_id, demandeur_id, holder_id, property_id})",
        "contact.demandeur_consented (payload: {contact_id, demandeur_id, timestamp})",
        "contact.holder_consented (payload: {contact_id, holder_id, timestamp})",
        "contact.holder_refused (payload: {contact_id, holder_id, reason})",
        "contact.consent_obtained (payload: {contact_id, demandeur_consent_at, holder_consent_at})",
        "contact.established (payload: {contact_id, activated_at, channel})",
        "contact.expired (payload: {contact_id, expiry_reason})",
        "contact.archived (payload: {contact_id, archive_reason})"
      ],
      "required_permissions": [
        "USER (demandeur): view own contacts, express interest",
        "USER (holder): view contacts for own properties, accept/reject",
        "AGENT: view contacts for assigned projects",
        "ADMIN: view all contacts, force establish"
      ],
      "required_states": [
        "Contact.state ∈ {created, demandeur_interested, holder_contacted, holder_favorable, consent_obtained, established, refused, expired}"
      ],
      "H0.5_matrices_impacted": ["consent_tracking", "holder_silence_escalation"],
      "implementation_priority": "P1",
      "implementation_wave": "Phase 1 — Core Business",
      "human_decision_required": true,
      "human_decision_question": "Double consent enforcement: mandatory for all contacts or configurable",
      "status": "APPROVED"
    },
    {
      "extension_id": "EXT-WF-003",
      "source_concept": "Visit Lifecycle (9 states)",
      "source_document": "WORKFLOW_STATE_CROSSWALK.md / WORKFLOW_05 (Gold)",
      "source_rule_ids": ["WORKFLOW_05"],
      "current_target": "No existing entity",
      "current_limitation": "No Visit entity or state machine in V2 (project step:visit is label only)",
      "extension_category": "workflow_specialized",
      "proposed_domain": "Domain 7: Visit Workflow",
      "proposed_entity": "Visit",
      "proposed_structure": "CREATE_SPECIALIZED_WORKFLOW — Implement Visit model with 9-state lifecycle; add scheduling, confirmation, no-show tracking, post-visit NBA",
      "decision": "CREATE_SPECIALIZED_WORKFLOW",
      "workflow_id": "visit_lifecycle",
      "entity_type": "Visit",
      "initial_state": "requested",
      "states": ["requested", "awaiting_confirmation", "confirmed", "completed", "rescheduled", "cancelled", "refused", "absent_demandeur", "absent_holder"],
      "terminal_states": ["completed", "cancelled", "refused"],
      "transitions": [
        {"from": "requested", "to": "awaiting_confirmation", "trigger": "holder_notified", "guard": "visit_proposed", "action": "notify_holder_and_start_timer"},
        {"from": "requested", "to": "cancelled", "trigger": "demandeur_cancels", "guard": "cancellation_allowed", "action": "process_cancellation"},
        {"from": "awaiting_confirmation", "to": "confirmed", "trigger": "holder_confirms", "guard": "confirmation_within_deadline", "action": "schedule_reminders"},
        {"from": "awaiting_confirmation", "to": "refused", "trigger": "holder_refuses", "guard": "holder_declines", "action": "notify_demandeur_and_offer_alternative"},
        {"from": "awaiting_confirmation", "to": "expired", "trigger": "confirmation_deadline_passed", "guard": "no_response_within_deadline", "action": "notify_both_and_offer_reschedule"},
        {"from": "confirmed", "to": "completed", "trigger": "visit_occurred", "guard": "visit_confirmed", "action": "record_completion_and_send_survey"},
        {"from": "confirmed", "to": "rescheduled", "trigger": "reschedule_requested", "guard": "both_agree", "action": "update_datetime_and_reassign_reminders"},
        {"from": "confirmed", "to": "cancelled", "trigger": "either_cancels", "guard": "cancellation_policy_ok", "action": "process_cancellation"},
        {"from": "confirmed", "to": "absent_demandeur", "trigger": "demandeur_no_show", "guard": "30min_post_scheduled", "action": "log_absence_and_offer_reschedule"},
        {"from": "confirmed", "to": "absent_holder", "trigger": "holder_no_show", "guard": "30min_post_scheduled", "action": "log_absence_and_offer_rematch"}
      ],
      "guards": [
        {"name": "visit_proposed", "condition": "Visit has valid datetime, property, and participants"},
        {"name": "cancellation_allowed", "condition": "Not within 2h of scheduled visit"},
        {"name": "confirmation_within_deadline", "condition": "Holder responds before deadline"},
        {"name": "holder_declines", "condition": "Holder explicitly refuses"},
        {"name": "no_response_within_deadline", "condition": "Confirmation deadline passed"},
        {"name": "visit_confirmed", "condition": "Visit occurred (confirmed by party or agent)"},
        {"name": "both_agree", "condition": "Both parties agree to new datetime"},
        {"name": "cancellation_policy_ok", "condition": "Within policy, no excessive cancellations"},
        {"name": "30min_post_scheduled", "condition": "30 minutes after scheduled start"}
      ],
      "triggers": [
        {"name": "holder_notified", "source": "System (notification)"},
        {"name": "demandeur_cancels", "source": "Demandeur action"},
        {"name": "holder_confirms", "source": "Holder action"},
        {"name": "holder_refuses", "source": "Holder action"},
        {"name": "confirmation_deadline_passed", "source": "System (cron)"},
        {"name": "visit_occurred", "source": "System (auto) or agent confirmation"},
        {"name": "reschedule_requested", "source": "Either party action"},
        {"name": "demandeur_no_show", "source": "System (cron, 30min after)"},
        {"name": "holder_no_show", "source": "System (cron, 30min after)"}
      ],
      "actions": [
        {"name": "notify_holder", "description": "Send visit request to holder", "async": true},
        {"name": "start_confirmation_timer", "description": "Set confirmation deadline", "async": true},
        {"name": "process_cancellation", "description": "Log and apply cancellation rules", "async": false},
        {"name": "schedule_reminders", "description": "Schedule 24h and 2h reminders", "async": true},
        {"name": "record_completion", "description": "Log completion timestamp", "async": false},
        {"name": "send_satisfaction_survey", "description": "Send post-visit survey", "async": true},
        {"name": "update_datetime", "description": "Update scheduled_at", "async": false},
        {"name": "log_absence", "description": "Record absence type and timestamp", "async": false},
        {"name": "offer_reschedule", "description": "Propose alternative time", "async": true},
        {"name": "offer_rematch", "description": "Propose new property match", "async": true}
      ],
      "SLA": [
        {"state": "awaiting_confirmation", "max_duration": "Until 24h before visit", "escalation": "Reminder to holder at 48h before"},
        {"state": "confirmed", "max_duration": "Until scheduled datetime", "escalation": "24h and 2h reminders"},
        {"state": "absent", "max_duration": "30min after scheduled", "escalation": "Immediate notification to other party"},
        {"state": "satisfaction", "max_duration": "1h post-visit", "escalation": "Reminder at 1h, 24h, auto-close"}
      ],
      "NBA_rules": [
        {"state": "requested", "nba": "Holder has been notified — awaiting confirmation"},
        {"state": "awaiting_confirmation", "nba": "Confirm or reschedule the visit (holder)"},
        {"state": "confirmed", "nba": "Visit scheduled — prepare documents"},
        {"state": "completed_satisfied", "nba": "Proceed to negotiation"},
        {"state": "completed_neutral", "nba": "Schedule a second visit"},
        {"state": "completed_unsatisfied", "nba": "View alternative properties"},
        {"state": "absent_demandeur", "nba": "Demandeur missed visit — offer reschedule"},
        {"state": "absent_holder", "nba": "Holder missed visit — offer rematch"},
        {"state": "cancelled", "nba": "View other available properties"}
      ],
      "events": [
        "visit.requested (project_id, property_id, demandeur_id, scheduled_at)",
        "visit.confirmed (visit_id, holder_id, confirmed_at)",
        "visit.rescheduled (visit_id, old_datetime, new_datetime, requested_by)",
        "visit.cancelled (visit_id, cancelled_by, reason)",
        "visit.refused (visit_id, refused_by, reason)",
        "visit.completed (visit_id, completed_at, notes)",
        "visit.absence_reported (visit_id, absent_party, absence_type)",
        "visit.satisfaction_recorded (visit_id, party, rating, feedback)",
        "visit.reminder_sent (visit_id, reminder_type, channel)"
      ],
      "failure_policy": {
        "double_booking": "Reject second visit, notify requester",
        "last_minute_cancellation": "Count toward trust penalty",
        "third_demandeur_no_show": "Reduce trust level, flag account",
        "third_holder_no_show": "Flag property, reduce holder reliability",
        "force_majeure": "Allow cancellation without penalty"
      },
      "required_fields": [
        "Visit.id: UUID",
        "Visit.project_id: UUID (FK → Project)",
        "Visit.property_id: UUID (FK → Property)",
        "Visit.demandeur_id: UUID (FK → User)",
        "Visit.holder_id: UUID (FK → User)",
        "Visit.agent_id: UUID? (FK → User)",
        "Visit.scheduled_at: DateTime",
        "Visit.state: Enum (9 states)",
        "Visit.confirmation_deadline: DateTime",
        "Visit.satisfaction_demandeur: Int? (1-5)",
        "Visit.satisfaction_holder: Int? (1-5)",
        "Visit.absence_type: Enum? (demandeur_no_show | holder_no_show)",
        "Visit.reminder_24h_sent: Boolean",
        "Visit.reminder_2h_sent: Boolean",
        "Visit.notes: Text",
        "Visit.created_at: DateTime",
        "Visit.completed_at: DateTime?"
      ],
      "required_relations": [
        "Visit.project_id → Project",
        "Visit.property_id → Property",
        "Visit.demandeur_id → User",
        "Visit.holder_id → User",
        "Visit.agent_id → User (agent)"
      ],
      "required_events": [
        "visit.requested (payload: {project_id, property_id, demandeur_id, scheduled_at})",
        "visit.confirmed (payload: {visit_id, holder_id, confirmed_at})",
        "visit.rescheduled (payload: {visit_id, old_datetime, new_datetime, requested_by})",
        "visit.cancelled (payload: {visit_id, cancelled_by, reason})",
        "visit.completed (payload: {visit_id, completed_at, notes})",
        "visit.absence_reported (payload: {visit_id, absent_party, absence_type})",
        "visit.satisfaction_recorded (payload: {visit_id, party, rating, feedback})"
      ],
      "required_permissions": [
        "USER (demandeur): request visits, cancel own visits",
        "USER (holder): confirm/refuse/reschedule visits",
        "AGENT: manage all visits for assigned projects",
        "ADMIN: view all visits, override"
      ],
      "required_states": [
        "Visit.state ∈ {requested, awaiting_confirmation, confirmed, completed, rescheduled, cancelled, refused, absent_demandeur, absent_holder}"
      ],
      "H0.5_matrices_impacted": ["reminder_system", "absence_handling", "satisfaction_tracking"],
      "implementation_priority": "P1",
      "implementation_wave": "Phase 1 — Core Business",
      "human_decision_required": false,
      "status": "APPROVED"
    },
    {
      "extension_id": "EXT-WF-004",
      "source_concept": "Transaction Lifecycle (10 states)",
      "source_document": "WORKFLOW_STATE_CROSSWALK.md / WORKFLOW_07 (Gold)",
      "source_rule_ids": ["WORKFLOW_07"],
      "current_target": "No existing entity",
      "current_limitation": "No Transaction entity or state machine in V2",
      "extension_category": "workflow_specialized",
      "proposed_domain": "Domain 9: Transaction Workflow",
      "proposed_entity": "Transaction",
      "proposed_structure": "CREATE_SPECIALIZED_WORKFLOW — Implement Transaction model with 10-state lifecycle; add per-type document requirements; party involvement tracking; payment milestones",
      "decision": "CREATE_SPECIALIZED_WORKFLOW",
      "workflow_id": "transaction_lifecycle",
      "entity_type": "Transaction",
      "initial_state": "agreement",
      "states": ["agreement", "preparation", "documents", "payment", "signature", "handover", "completed", "failed", "archived", "cancelled", "disputed"],
      "terminal_states": ["completed", "failed", "archived", "cancelled"],
      "transitions": [
        {"from": "agreement", "to": "preparation", "trigger": "terms_agreed", "guard": "agreement_valid", "action": "initiate_preparation"},
        {"from": "agreement", "to": "cancelled", "trigger": "deal_off", "guard": "cancellation_allowed", "action": "cancel_transaction"},
        {"from": "preparation", "to": "documents", "trigger": "preparation_complete", "guard": "all_preparation_done", "action": "request_documents"},
        {"from": "documents", "to": "payment", "trigger": "documents_approved", "guard": "all_documents_valid", "action": "initiate_payment_milestones"},
        {"from": "documents", "to": "preparation", "trigger": "documents_rejected", "guard": "docs_incomplete", "action": "request_corrections"},
        {"from": "payment", "to": "signature", "trigger": "payment_complete", "guard": "all_milestones_paid", "action": "schedule_signature"},
        {"from": "payment", "to": "failed", "trigger": "payment_default", "guard": "payment_breach", "action": "handle_payment_failure"},
        {"from": "signature", "to": "handover", "trigger": "all_signed", "guard": "signatures_valid", "action": "schedule_handover"},
        {"from": "signature", "to": "failed", "trigger": "signature_refused", "guard": "party_refuses", "action": "handle_signature_failure"},
        {"from": "handover", "to": "completed", "trigger": "handover_done", "guard": "keys_transferred", "action": "finalize_transaction"},
        {"from": "handover", "to": "disputed", "trigger": "handover_disputed", "guard": "dispute_filed", "action": "initiate_dispute"},
        {"from": "completed", "to": "archived", "trigger": "archival_period", "guard": "90d_post_completion", "action": "archive"},
        {"from": "completed", "to": "disputed", "trigger": "post_completion_dispute", "guard": "within_legal_period", "action": "reopen_dispute"},
        {"from": "failed", "to": "archived", "trigger": "failure_archived", "guard": "30d_post_failure", "action": "archive"}
      ],
      "guards": [
        {"name": "agreement_valid", "condition": "Agreement has all required terms"},
        {"name": "cancellation_allowed", "condition": "Cancellation within allowed period"},
        {"name": "all_preparation_done", "condition": "Preparation steps completed"},
        {"name": "all_documents_valid", "condition": "All mandatory docs uploaded and validated"},
        {"name": "docs_incomplete", "condition": "Missing or invalid documents"},
        {"name": "all_milestones_paid", "condition": "All payment milestones completed"},
        {"name": "payment_breach", "condition": "Payment milestone missed or failed"},
        {"name": "signatures_valid", "condition": "All parties have signed"},
        {"name": "party_refuses", "condition": "Party refuses to sign"},
        {"name": "keys_transferred", "condition": "Keys/handover completed"},
        {"name": "dispute_filed", "condition": "Formal dispute registered"},
        {"name": "90d_post_completion", "condition": "90 days after completion"},
        {"name": "within_legal_period", "condition": "Within legal challenge period"}
      ],
      "triggers": [
        {"name": "terms_agreed", "source": "Both parties"},
        {"name": "preparation_complete", "source": "System/agent"},
        {"name": "documents_approved", "source": "Admin validation"},
        {"name": "payment_complete", "source": "Payment provider"},
        {"name": "all_signed", "source": "Signature service"},
        {"name": "handover_done", "source": "Agent confirmation"},
        {"name": "payment_default", "source": "System (cron)"}
      ],
      "actions": [
        {"name": "initiate_preparation", "description": "Begin transaction preparation", "async": false},
        {"name": "request_documents", "description": "Request per-type required docs", "async": true},
        {"name": "initiate_payment_milestones", "description": "Setup payment schedule", "async": false},
        {"name": "schedule_signature", "description": "Arrange signing session", "async": true},
        {"name": "handle_payment_failure", "description": "Apply payment failure policy", "async": false},
        {"name": "finalize_transaction", "description": "Complete transaction record", "async": false},
        {"name": "initiate_dispute", "description": "Create linked incident", "async": true},
        {"name": "cancel_transaction", "description": "Cancel with reason", "async": false}
      ],
      "SLA": [
        {"state": "preparation", "max_duration": "7d", "escalation": "Reminder at 3d, 5d"},
        {"state": "documents", "max_duration": "14d", "escalation": "Reminder at 7d, 10d, auto-escalate"},
        {"state": "payment", "max_duration": "Per milestone", "escalation": "Reminder 3d before, breach at due date"},
        {"state": "signature", "max_duration": "7d", "escalation": "Reminder at 3d, 5d"}
      ],
      "NBA_rules": [
        {"state": "agreement", "nba": "Formalize agreement terms"},
        {"state": "preparation", "nba": "Prepare transaction documents"},
        {"state": "documents", "nba": "Submit required documents"},
        {"state": "payment", "nba": "Complete payment milestones"},
        {"state": "signature", "nba": "Sign transaction documents"},
        {"state": "handover", "nba": "Schedule key handover"},
        {"state": "completed", "nba": "Transaction completed — follow up in 90d"},
        {"state": "failed", "nba": "Review failure reason and options"}
      ],
      "events": [
        "transaction.created (project_id, property_id, transaction_type, parties)",
        "transaction.agreement_reached (transaction_id, terms_summary)",
        "transaction.preparation_complete (transaction_id)",
        "transaction.documents_submitted (transaction_id, document_ids)",
        "transaction.payment_milestone (transaction_id, milestone, amount, paid_at)",
        "transaction.signed (transaction_id, party, signed_at)",
        "transaction.handover (transaction_id, handover_at, notes)",
        "transaction.completed (transaction_id, completed_at, price_final)",
        "transaction.failed (transaction_id, failure_reason, failed_at)",
        "transaction.disputed (transaction_id, dispute_reason, disputed_at)",
        "transaction.archived (transaction_id, archived_at)"
      ],
      "failure_policy": {
        "payment_default": "Apply penalty, offer cure period (7d), then fail",
        "signature_refusal": "Attempt mediation, then fail with reason",
        "document_deficiency": "14d cure period with reminders",
        "post_completion_dispute": "Route to incident/mediation workflow"
      },
      "required_fields": [
        "Transaction.id: UUID",
        "Transaction.project_id: UUID (FK → Project)",
        "Transaction.property_id: UUID (FK → Property)",
        "Transaction.transaction_type: Enum (sale | rental | lease | commercial_lease | seasonal_rental | investment)",
        "Transaction.state: Enum (11 states)",
        "Transaction.demandeur_id: UUID (FK → User)",
        "Transaction.holder_id: UUID (FK → User)",
        "Transaction.agent_id: UUID? (FK → User)",
        "Transaction.notaire_id: UUID? (FK → User)",
        "Transaction.price_agreed: Decimal",
        "Transaction.currency: String (XAF)",
        "Transaction.payment_milestones: JSON[]",
        "Transaction.signature_demandeur_at: DateTime?",
        "Transaction.signature_holder_at: DateTime?",
        "Transaction.handover_at: DateTime?",
        "Transaction.completed_at: DateTime?",
        "Transaction.failed_at: DateTime?",
        "Transaction.failure_reason: String?"
      ],
      "required_relations": [
        "Transaction.project_id → Project",
        "Transaction.property_id → Property"
      ],
      "required_events": [
        "transaction.created (payload: {project_id, property_id, transaction_type, demandeur_id, holder_id})",
        "transaction.documents_submitted (payload: {transaction_id, document_ids[]})",
        "transaction.payment_milestone (payload: {transaction_id, milestone, amount, paid_at})",
        "transaction.signed (payload: {transaction_id, party, signed_at})",
        "transaction.handover (payload: {transaction_id, handover_at, notes})",
        "transaction.completed (payload: {transaction_id, completed_at, price_final})",
        "transaction.failed (payload: {transaction_id, failure_reason, failed_at})"
      ],
      "required_permissions": [
        "USER (party): view own transactions",
        "AGENT: manage assigned transactions",
        "NOTAIRE: view legal transactions",
        "ADMIN: view all, force state change"
      ],
      "required_states": [
        "Transaction.state ∈ {agreement, preparation, documents, payment, signature, handover, completed, failed, archived, cancelled, disputed}"
      ],
      "H0.5_matrices_impacted": ["document_requirements", "payment_milestones", "signature_tracking"],
      "implementation_priority": "P1",
      "implementation_wave": "Phase 1 — Core Business",
      "human_decision_required": true,
      "human_decision_question": "Transaction entity vs extended Project: separate model or project extension",
      "status": "APPROVED"
    },
    {
      "extension_id": "EXT-WF-005",
      "source_concept": "Paid Services & Payment Lifecycle (18 states)",
      "source_document": "WORKFLOW_STATE_CROSSWALK.md / WORKFLOW_08 (Gold)",
      "source_rule_ids": ["WORKFLOW_08"],
      "current_target": "No existing entity",
      "current_limitation": "No payment or service system exists in V2",
      "extension_category": "workflow_generic_state_machine",
      "proposed_domain": "Domain 3: Service Model",
      "proposed_entity": "ServiceOrder + Payment",
      "proposed_structure": "CREATE_NEW_GENERIC_STATE_MACHINE — Implement ServiceOrder model with 8-state lifecycle and Payment model with 10-state sub-machine; integrate Campay payment processor",
      "decision": "CREATE_NEW_GENERIC_STATE_MACHINE",
      "workflow_id": "paid_services_and_payment",
      "entity_type": "ServiceOrder, Payment",
      "initial_state": "creation (ServiceOrder), created (Payment)",
      "states_service_order": ["creation", "proposition", "acceptation", "paiement", "activation", "utilisation", "expiration", "archivage"],
      "states_payment": ["created", "initiated", "pending", "confirmed", "failed", "cancelled", "expired", "refunded", "reconciled", "disputed"],
      "terminal_states_service_order": ["archivage", "expiration"],
      "terminal_states_payment": ["confirmed", "failed", "cancelled", "expired", "refunded", "reconciled"],
      "transitions_service_order": [
        {"from": "creation", "to": "proposition", "trigger": "service_selected", "guard": "service_valid", "action": "create_proposition_and_notify_buyer"},
        {"from": "proposition", "to": "acceptation", "trigger": "buyer_accepts", "guard": "acceptance_valid", "action": "record_acceptance_and_initiate_payment"},
        {"from": "proposition", "to": "archivage", "trigger": "buyer_declines", "guard": "decline_reason", "action": "log_decline_and_archive"},
        {"from": "proposition", "to": "expiration", "trigger": "offer_expires", "guard": "30d_no_action", "action": "auto_expire"},
        {"from": "acceptation", "to": "paiement", "trigger": "payment_initiated", "guard": "payment_created", "action": "link_payment_and_wait"},
        {"from": "paiement", "to": "activation", "trigger": "payment_confirmed", "guard": "payment_successful", "action": "activate_service"},
        {"from": "paiement", "to": "archivage", "trigger": "payment_failed_max", "guard": "payment_failed_max_retries", "action": "log_failure"},
        {"from": "activation", "to": "utilisation", "trigger": "service_accessed", "guard": "service_active", "action": "track_usage"},
        {"from": "utilisation", "to": "expiration", "trigger": "service_expires", "guard": "duration_exceeded", "action": "deactivate_and_notify"},
        {"from": "utilisation", "to": "archivage", "trigger": "service_completed", "guard": "usage_complete", "action": "finalize_and_archive"}
      ],
      "transitions_payment": [
        {"from": "created", "to": "initiated", "trigger": "payment_started", "guard": "provider_available", "action": "send_to_provider"},
        {"from": "initiated", "to": "pending", "trigger": "provider_acknowledged", "guard": "ack_received", "action": "start_confirmation_timer"},
        {"from": "pending", "to": "confirmed", "trigger": "provider_confirms", "guard": "confirmation_received", "action": "record_confirmation"},
        {"from": "pending", "to": "failed", "trigger": "provider_rejects", "guard": "failure_reason", "action": "log_failure"},
        {"from": "pending", "to": "expired", "trigger": "confirmation_timeout", "guard": "30min_no_response", "action": "mark_expired"},
        {"from": "initiated", "to": "cancelled", "trigger": "user_cancels", "guard": "cancellation_allowed", "action": "process_cancellation"},
        {"from": "confirmed", "to": "refunded", "trigger": "refund_requested", "guard": "refund_policy_ok", "action": "process_refund"},
        {"from": "confirmed", "to": "reconciled", "trigger": "reconciliation_run", "guard": "end_of_day", "action": "mark_reconciled"},
        {"from": "confirmed", "to": "disputed", "trigger": "dispute_filed", "guard": "dispute_valid", "action": "flag_dispute"},
        {"from": "disputed", "to": "refunded", "trigger": "dispute_resolved_refund", "guard": "admin_decision_refund", "action": "process_refund"},
        {"from": "disputed", "to": "confirmed", "trigger": "dispute_resolved_keep", "guard": "admin_decision_keep", "action": "resolve_dispute"},
        {"from": "failed", "to": "initiated", "trigger": "retry", "guard": "retry_count_lt_max", "action": "reinitiate_payment"},
        {"from": "expired", "to": "initiated", "trigger": "retry", "guard": "retry_allowed", "action": "reinitiate_payment"}
      ],
      "guards": [
        {"name": "service_valid", "condition": "Service exists, is_active, and available"},
        {"name": "acceptance_valid", "condition": "Buyer agreed to price and terms"},
        {"name": "payment_successful", "condition": "Payment provider confirmed success"},
        {"name": "provider_available", "condition": "Payment provider reachable"},
        {"name": "confirmation_received", "condition": "Valid confirmation from provider"},
        {"name": "retry_allowed", "condition": "Retry count < max AND time since last > 5min"},
        {"name": "30min_no_response", "condition": "No provider callback within 30min"},
        {"name": "refund_policy_ok", "condition": "Within refund policy (7d, unused)"}
      ],
      "SLA": [
        {"state": "pending (payment)", "max_duration": "30min", "escalation": "Auto-check every 5min"},
        {"state": "proposition", "max_duration": "30d", "escalation": "Auto-expire"},
        {"state": "utilisation", "max_duration": "Per service", "escalation": "Notify 7d before expiry"}
      ],
      "NBA_rules": [
        {"state": "creation", "nba": "Select service to purchase"},
        {"state": "proposition", "nba": "Review and accept service offer"},
        {"state": "acceptation", "nba": "Complete payment"},
        {"state": "paiement", "nba": "Awaiting payment confirmation"},
        {"state": "activation", "nba": "Service is active — start using"},
        {"state": "utilisation", "nba": "Service in use or expiring soon"},
        {"state": "expiration", "nba": "Service expired — repurchase or upgrade"}
      ],
      "events": [
        "service_order.created (order_id, service_id, buyer_id, price)",
        "service_order.proposed (order_id, proposition_details, expires_at)",
        "service_order.accepted (order_id, accepted_at)",
        "service_order.activated (order_id, activated_at, duration_days)",
        "service_order.expired (order_id, expired_at)",
        "payment.created (payment_id, order_id, amount, provider)",
        "payment.initiated (payment_id, provider_reference)",
        "payment.confirmed (payment_id, confirmed_at, provider_ref)",
        "payment.failed (payment_id, failure_reason, failure_code)",
        "payment.refunded (payment_id, refunded_at, refund_amount)",
        "payment.disputed (payment_id, dispute_reason, disputed_at)",
        "payment.reconciled (payment_id, reconciled_at)"
      ],
      "failure_policy": {
        "provider_timeout": "Retry (max 3, 5min interval), then expire",
        "insufficient_funds": "Notify buyer, offer alternative",
        "network_failure": "Queue, retry with exponential backoff",
        "duplicate_callback": "Idempotency key, reconcile duplicate",
        "refund_failure": "Manual intervention, admin notified"
      },
      "required_fields": [
        "ServiceOrder.id: UUID",
        "ServiceOrder.service_id: UUID (FK → Service)",
        "ServiceOrder.buyer_id: UUID (FK → User)",
        "ServiceOrder.property_id: UUID?",
        "ServiceOrder.project_id: UUID?",
        "ServiceOrder.price_paid: Decimal",
        "ServiceOrder.currency: String",
        "ServiceOrder.state: Enum (8 states)",
        "ServiceOrder.activated_at: DateTime?",
        "ServiceOrder.expires_at: DateTime?",
        "Payment.id: UUID",
        "Payment.service_order_id: UUID (FK → ServiceOrder)",
        "Payment.amount: Decimal",
        "Payment.currency: String",
        "Payment.provider: String (campay)",
        "Payment.phone_number: String",
        "Payment.state: Enum (10 states)",
        "Payment.provider_reference: String?",
        "Payment.confirmed_at: DateTime?",
        "Payment.failed_at: DateTime?",
        "Payment.failure_reason: String?",
        "Payment.refunded_at: DateTime?"
      ],
      "required_relations": [
        "ServiceOrder.service_id → Service",
        "ServiceOrder.buyer_id → User",
        "Payment.service_order_id → ServiceOrder"
      ],
      "required_events": [
        "service_order.created (payload: {order_id, service_id, buyer_id, price})",
        "service_order.proposed (payload: {order_id, proposition_details, expires_at})",
        "service_order.accepted (payload: {order_id, accepted_at})",
        "service_order.activated (payload: {order_id, activated_at, duration_days})",
        "payment.created (payload: {payment_id, order_id, amount})",
        "payment.initiated (payload: {payment_id, provider_reference})",
        "payment.confirmed (payload: {payment_id, confirmed_at, provider_ref})",
        "payment.failed (payload: {payment_id, failure_reason})",
        "payment.refunded (payload: {payment_id, refunded_at, refund_amount})",
        "payment.disputed (payload: {payment_id, dispute_reason})"
      ],
      "required_permissions": [
        "USER: purchase services",
        "AGENT: purchase services for clients",
        "ADMIN: view all orders, process refunds"
      ],
      "required_states": [
        "ServiceOrder.state ∈ {creation, proposition, acceptation, paiement, activation, utilisation, expiration, archivage}",
        "Payment.state ∈ {created, initiated, pending, confirmed, failed, cancelled, expired, refunded, reconciled, disputed}"
      ],
      "H0.5_matrices_impacted": ["service_catalog", "payment_processing"],
      "implementation_priority": "P1",
      "implementation_wave": "Phase 1 — Core Business",
      "human_decision_required": true,
      "human_decision_question": "Payment processor, service catalog scope, pricing validation",
      "status": "APPROVED"
    },
    {
      "extension_id": "EXT-WF-006",
      "source_concept": "Disputes, Claims & Incidents Lifecycle (8 states)",
      "source_document": "WORKFLOW_STATE_CROSSWALK.md / WORKFLOW_09 (Gold)",
      "source_rule_ids": ["WORKFLOW_09"],
      "current_target": "No existing entity",
      "current_limitation": "No incident management system in V2",
      "extension_category": "workflow_specialized",
      "proposed_domain": "Domain 9: Transaction Workflow (dispute sub-workflow)",
      "proposed_entity": "Incident",
      "proposed_structure": "CREATE_SPECIALIZED_WORKFLOW — Implement Incident model with 8-state lifecycle; 12 incident types; 4 priority levels (P0-P3)",
      "decision": "CREATE_SPECIALIZED_WORKFLOW",
      "workflow_id": "disputes_claims_incidents",
      "entity_type": "Incident",
      "initial_state": "reported",
      "states": ["reported", "qualified", "investigation", "analysis", "decision", "resolution", "closed", "reopened", "escalated"],
      "terminal_states": ["closed"],
      "incident_types": ["payment_dispute", "property_misrepresentation", "fraud_suspicion", "contract_breach", "no_show", "harassment", "data_privacy", "technical_issue", "agent_misconduct", "quality_complaint", "third_party", "other"],
      "priority_levels": ["P0 (Critical): response < 1h, resolution < 24h", "P1 (High): response < 4h, resolution < 72h", "P2 (Medium): response < 24h, resolution < 7d", "P3 (Low): response < 72h, resolution < 30d"],
      "SLA": [
        {"priority": "P0", "response": "< 1h", "resolution": "< 24h"},
        {"priority": "P1", "response": "< 4h", "resolution": "< 72h"},
        {"priority": "P2", "response": "< 24h", "resolution": "< 7d"},
        {"priority": "P3", "response": "< 72h", "resolution": "< 30d"}
      ],
      "events": [
        "incident.reported (incident_id, reporter_id, type, description, related_entity)",
        "incident.qualified (incident_id, priority, handler_id)",
        "incident.investigation_started (incident_id, started_at)",
        "incident.evidence_collected (incident_id, evidence_items)",
        "incident.analysis_complete (incident_id, findings_summary, recommendation)",
        "incident.decision_made (incident_id, decision, decided_by)",
        "incident.resolved (incident_id, resolution_actions)",
        "incident.closed (incident_id, closed_at)",
        "incident.reopened (incident_id, reason)",
        "incident.escalated (incident_id, escalated_to, reason)"
      ],
      "failure_policy": {
        "handler_no_response": "Reassign after 24h (P0-P1) or 72h (P2-P3)",
        "insufficient_evidence": "Mark inconclusive, notify parties",
        "sla_breach": "Escalate to next tier handler",
        "conflict_of_interest": "Reassign to alternate handler"
      },
      "implementation_priority": "P2",
      "implementation_wave": "Phase 2 — Operations",
      "human_decision_required": true,
      "human_decision_question": "Incident priority levels and SLA thresholds",
      "status": "APPROVED"
    },
    {
      "extension_id": "EXT-WF-007",
      "source_concept": "Mediation Workflow (8 states)",
      "source_document": "WORKFLOW_STATE_CROSSWALK.md / WORKFLOW_11 (Gold)",
      "source_rule_ids": ["WORKFLOW_11"],
      "current_target": "No existing entity",
      "current_limitation": "No mediation system exists in V2",
      "extension_category": "workflow_specialized",
      "proposed_domain": "Domain 9: Transaction Workflow (mediation sub-workflow)",
      "proposed_entity": "Mediation",
      "proposed_structure": "CREATE_SPECIALIZED_WORKFLOW — Implement Mediation model with 8-state lifecycle; define mediator role and boundaries; session management; offer/acceptance flow",
      "decision": "CREATE_SPECIALIZED_WORKFLOW",
      "workflow_id": "mediation_workflow",
      "entity_type": "Mediation",
      "initial_state": "filed",
      "states": ["filed", "assigned", "preliminary_review", "mediation_session", "offer_proposed", "accepted", "rejected", "closed", "escalated"],
      "terminal_states": ["accepted", "rejected", "closed", "escalated"],
      "events": [
        "mediation.filed (mediation_id, incident_id, filer_id, respondent_id, issue_summary)",
        "mediation.assigned (mediation_id, mediator_id, assigned_at)",
        "mediation.session_scheduled (mediation_id, session_datetime, format)",
        "mediation.offer_proposed (mediation_id, offer_summary, deadline)",
        "mediation.accepted (mediation_id, accepted_at, accepted_by_both)",
        "mediation.rejected (mediation_id, rejected_by, reason)",
        "mediation.escalated (mediation_id, escalated_to, reason)",
        "mediation.closed (mediation_id, outcome, closed_at)"
      ],
      "failure_policy": {
        "party_no_show": "Reschedule once, proceed in absentia",
        "mediator_unavailable": "Reassign within 24h",
        "agreement_not_honored": "Refer to legal escalation",
        "conflict_of_interest": "Reassign mediator immediately"
      },
      "implementation_priority": "P3",
      "implementation_wave": "Phase 4 — Enhancement",
      "human_decision_required": true,
      "human_decision_question": "Mediation as built-in platform feature vs outsourced service",
      "status": "APPROVED"
    },
    {
      "extension_id": "EXT-WF-008",
      "source_concept": "CRM Pipeline (8 stages)",
      "source_document": "WORKFLOW_STATE_CROSSWALK.md / WORKFLOW_18 (Gold)",
      "source_rule_ids": ["WORKFLOW_18", "CRM_MODEL.md"],
      "current_target": "No existing entity",
      "current_limitation": "No CRM pipeline exists in V2",
      "extension_category": "workflow_generic_state_machine",
      "proposed_domain": "Domain 10: CRM Pipeline",
      "proposed_entity": "Lead",
      "proposed_structure": "CREATE_NEW_GENERIC_STATE_MACHINE — Implement Lead model with 8-stage pipeline; scoring engine (base + 13 boosters - 8 penalties); 5-class classification; geographic routing engine; 4-layer anti-fraud",
      "decision": "CREATE_NEW_GENERIC_STATE_MACHINE",
      "workflow_id": "crm_pipeline",
      "entity_type": "Lead",
      "initial_state": "incoming",
      "states": ["incoming", "normalized", "extracted", "intent_detected", "enriched", "scored", "classified", "routed", "converted", "closed", "quarantined"],
      "terminal_states": ["routed", "converted", "closed", "quarantined"],
      "SLA": [
        {"classification": "HOT (80-100+)", "response": "< 30min (P0)", "assignment": "Immediate"},
        {"classification": "WARM (60-79)", "response": "< 2h (P1)", "assignment": "Priority"},
        {"classification": "COLD (40-59)", "response": "< 24h (P2)", "assignment": "Standard"},
        {"classification": "LOW (20-39)", "response": "< 7d (P3)", "assignment": "Batch"},
        {"classification": "SPAM (< 20)", "response": "N/A", "assignment": "Quarantine"}
      ],
      "events": [
        "lead.created (lead_id, source_channel, phone, name, initial_text)",
        "lead.normalized (lead_id, normalized_text, language)",
        "lead.fraud_flagged (lead_id, fraud_layers[], action_taken)",
        "lead.intent_detected (lead_id, intent, confidence, method)",
        "lead.scored (lead_id, base_score, boosters, penalties, final_score)",
        "lead.classified (lead_id, classification, score_range)",
        "lead.routed (lead_id, agent_id, routing_method, sla_deadline)",
        "lead.sla_breached (lead_id, sla_priority, breach_type)",
        "lead.converted (lead_id, project_id, converted_at)",
        "lead.closed (lead_id, outcome, reason)"
      ],
      "failure_policy": {
        "nlp_pipeline_failure": "Fallback to manual processing",
        "no_entity_extraction": "Skip to intent with minimal data",
        "no_agent_available": "Expand to nearest zone, notify manager",
        "scoring_engine_failure": "Use default base score",
        "fraud_false_positive": "Manual review queue, agent override"
      },
      "implementation_priority": "P1",
      "implementation_wave": "Phase 1 — Core Business",
      "human_decision_required": true,
      "human_decision_question": "CRM pipeline automation level: fully automated or human-in-the-loop",
      "status": "APPROVED"
    },
    {
      "extension_id": "EXT-WF-009",
      "source_concept": "Publication SIE-Enriched (11 states)",
      "source_document": "WORKFLOW_STATE_CROSSWALK.md / WORKFLOW_15 (Gold)",
      "source_rule_ids": ["WORKFLOW_15"],
      "current_target": "No existing entity",
      "current_limitation": "No SIE publication pipeline exists in V2",
      "extension_category": "workflow_specialized",
      "proposed_domain": "Domain 2: Property/Listing Model (publication sub-workflow)",
      "proposed_entity": "Publication",
      "proposed_structure": "CREATE_SPECIALIZED_WORKFLOW — Implement Publication model with 11-state lifecycle; SIE reference code generation; campaign association; syndication to channels; performance monitoring",
      "decision": "CREATE_SPECIALIZED_WORKFLOW",
      "workflow_id": "publication_sie",
      "entity_type": "Publication",
      "initial_state": "draft",
      "states": ["draft", "content_preparation", "media_validation", "sie_code_generation", "campaign_association", "quality_check", "published", "syndicated", "performance_monitoring", "expired", "archived"],
      "terminal_states": ["published", "archived", "expired"],
      "failure_policy": {
        "sie_code_collision": "Regenerate with different seed",
        "media_quality_fail": "Flag specific issues, allow manual override",
        "campaign_association_fail": "Publish without campaign, retry",
        "syndication_unavailable": "Queue for retry, notify operator"
      },
      "implementation_priority": "P3",
      "implementation_wave": "Phase 3 — Analytics",
      "human_decision_required": true,
      "human_decision_question": "SIE integration priority: required for MVP or Phase 3 enhancement",
      "status": "APPROVED"
    },
    {
      "extension_id": "EXT-WF-010",
      "source_concept": "Redirection SIE-Enriched (12 states)",
      "source_document": "WORKFLOW_STATE_CROSSWALK.md / WORKFLOW_16 (Gold)",
      "source_rule_ids": ["WORKFLOW_16"],
      "current_target": "No existing entity",
      "current_limitation": "No redirection/click tracking pipeline in V2",
      "extension_category": "workflow_specialized",
      "proposed_domain": "Domain 10: CRM Pipeline (analytics sub-workflow)",
      "proposed_entity": "Redirection",
      "proposed_structure": "CREATE_SPECIALIZED_WORKFLOW — Implement Redirection model with 12-state lifecycle; bot detection; duplicate detection; geolocation; analytics enrichment; campaign attribution",
      "decision": "CREATE_SPECIALIZED_WORKFLOW",
      "workflow_id": "redirection_sie",
      "entity_type": "Redirection",
      "initial_state": "click_received",
      "states": ["click_received", "user_agent_parsed", "bot_detection", "duplicate_detection", "geolocation", "analytics_enrichment", "campaign_attribution", "conversion_check", "redirect_executed", "conversion_logged", "expired", "archived"],
      "terminal_states": ["redirect_executed", "conversion_logged", "archived"],
      "failure_policy": {
        "geolocation_unavailable": "Proceed with IP-based fallback",
        "bot_false_negative": "Periodic audit of redirected traffic",
        "dedup_false_positive": "Allow through, log for analysis",
        "target_unavailable": "Log error, return 302 to fallback"
      },
      "implementation_priority": "P3",
      "implementation_wave": "Phase 3 — Analytics",
      "human_decision_required": false,
      "status": "APPROVED"
    },
    {
      "extension_id": "EXT-WF-011",
      "source_concept": "Conversion & Attribution (12 states)",
      "source_document": "WORKFLOW_STATE_CROSSWALK.md / WORKFLOW_17 (Gold)",
      "source_rule_ids": ["WORKFLOW_17"],
      "current_target": "No existing entity",
      "current_limitation": "No conversion attribution pipeline in V2",
      "extension_category": "workflow_specialized",
      "proposed_domain": "Domain 10: CRM Pipeline (attribution sub-workflow)",
      "proposed_entity": "Conversion",
      "proposed_structure": "CREATE_SPECIALIZED_WORKFLOW — Implement Conversion model with 12-state lifecycle; last-touch attribution; session identification; source/campaign mapping; commission calculation",
      "decision": "CREATE_SPECIALIZED_WORKFLOW",
      "workflow_id": "conversion_attribution",
      "entity_type": "Conversion",
      "initial_state": "touchpoint_detected",
      "states": ["touchpoint_detected", "session_identified", "source_attributed", "campaign_mapped", "conversion_type_determined", "lead_generated", "project_created", "transaction_completed", "commission_calculated", "attributed", "reported", "archived"],
      "terminal_states": ["attributed", "reported", "archived"],
      "failure_policy": {
        "session_id_failure": "Store anonymous, retroactively link",
        "unrecognized_campaign": "Log unknown, proceed without",
        "attribution_model_error": "Default to equal, flag for review",
        "commission_calculation_error": "Manual override available"
      },
      "implementation_priority": "P3",
      "implementation_wave": "Phase 3 — Analytics",
      "human_decision_required": true,
      "human_decision_question": "Attribution model: last-touch (Gold) or multi-touch",
      "status": "APPROVED"
    },
    {
      "extension_id": "EXT-WF-012",
      "source_concept": "Agent Invitation Workflow (7 states)",
      "source_document": "WORKFLOW_STATE_CROSSWALK.md / WORKFLOW_14 (Gold)",
      "source_rule_ids": ["WORKFLOW_14", "GOLD-RL-035"],
      "current_target": "No existing entity",
      "current_limitation": "No agent invitation/onboarding workflow in V2",
      "extension_category": "workflow_specialized",
      "proposed_domain": "Domain 12: Organization Model (agent sub-workflow)",
      "proposed_entity": "AgentInvitation",
      "proposed_structure": "CREATE_SPECIALIZED_WORKFLOW — Implement AgentInvitation model with 7-state lifecycle; secure link generation; document validation; admin approval workflow",
      "decision": "CREATE_SPECIALIZED_WORKFLOW",
      "workflow_id": "agent_invitation",
      "entity_type": "AgentInvitation",
      "initial_state": "invitation_sent",
      "states": ["invitation_sent", "link_opened", "account_created", "phone_verified", "cni_uploaded", "validated", "active", "expired", "revoked"],
      "terminal_states": ["active", "expired", "revoked"],
      "failure_policy": {
        "link_expiry": "Allow inviter to resend (max 3)",
        "otp_failure": "Allow retry (max 5), lock for 1h",
        "document_rejection": "Clear reason, allow re-upload",
        "admin_no_response": "Escalate after 7d, reassign"
      },
      "implementation_priority": "P2",
      "implementation_wave": "Phase 2 — Operations",
      "human_decision_required": true,
      "human_decision_question": "Onboarding step requirements: all Gold steps or simplified flow",
      "status": "APPROVED"
    },
    {
      "extension_id": "EXT-WF-013",
      "source_concept": "Identity Resolution Workflow (5 states)",
      "source_document": "WORKFLOW_STATE_CROSSWALK.md / WORKFLOW_20 (Gold)",
      "source_rule_ids": ["WORKFLOW_20"],
      "current_target": "No existing entity",
      "current_limitation": "No identity resolution exists in V2",
      "extension_category": "workflow_specialized",
      "proposed_domain": "Domain 11: Identity Model",
      "proposed_entity": "IdentityResolution",
      "proposed_structure": "CREATE_SPECIALIZED_WORKFLOW — Implement IdentityResolution model with 5-state lifecycle; signal matching (phone 0.40, email 0.35, name 0.15, device 0.10); auto-merge at >= 0.90 + phone match; human review at 0.70-0.89",
      "decision": "CREATE_SPECIALIZED_WORKFLOW",
      "workflow_id": "identity_resolution",
      "entity_type": "IdentityResolution",
      "initial_state": "detected",
      "states": ["detected", "matched", "reviewed", "merged", "resolved", "rejected"],
      "terminal_states": ["resolved", "rejected"],
      "failure_policy": {
        "incorrect_auto_merge": "Rollback within 30d window",
        "merge_conflict": "Survivor strategy (most recent active)",
        "data_inconsistency": "Audit log for manual reconciliation"
      },
      "implementation_priority": "P3",
      "implementation_wave": "Phase 4 — Enhancement",
      "human_decision_required": true,
      "human_decision_question": "Identity resolution automation level and false positive handling",
      "status": "APPROVED"
    },
    {
      "extension_id": "EXT-WF-014",
      "source_concept": "Main Cross-cutting Workflow (9 states)",
      "source_document": "WORKFLOW_STATE_CROSSWALK.md / WORKFLOW_21 (Gold)",
      "source_rule_ids": ["WORKFLOW_21"],
      "current_target": "Project entity (V2)",
      "current_limitation": "V2 has no orchestrator; workflows are distributed across project, property, conversation models",
      "extension_category": "workflow_generic_state_machine",
      "proposed_domain": "Domain 5: Dossier/Project Model (orchestrator)",
      "proposed_entity": "Project (orchestrator)",
      "proposed_structure": "CREATE_NEW_GENERIC_STATE_MACHINE — Implement orchestrator workflow engine that delegates to sub-workflows (Qualification → Matching → Contact → Visit → Negotiation → Transaction → Closure). Generic engine pattern reusable across entities.",
      "decision": "CREATE_NEW_GENERIC_STATE_MACHINE",
      "workflow_id": "main_cross_cutting",
      "entity_type": "Project",
      "initial_state": "creation",
      "states": ["creation", "qualification", "matching", "double_consent", "mise_en_relation", "visit", "negotiation", "transaction", "closure", "archive", "cancelled"],
      "terminal_states": ["closure", "archive", "cancelled"],
      "delegated_sub_workflows": [
        {"orchestrator_state": "qualification", "workflow": "Qualification Workflow (10 steps)"},
        {"orchestrator_state": "matching", "workflow": "Matching Lifecycle (WF-001)"},
        {"orchestrator_state": "double_consent", "workflow": "Mise en Relation (WF-002)"},
        {"orchestrator_state": "mise_en_relation", "workflow": "Mise en Relation (WF-002)"},
        {"orchestrator_state": "visit", "workflow": "Visit Lifecycle (WF-003)"},
        {"orchestrator_state": "negotiation", "workflow": "Negotiation Workflow"},
        {"orchestrator_state": "transaction", "workflow": "Transaction Lifecycle (WF-004)"}
      ],
      "failure_policy": {
        "sub_workflow_failure": "Capture failure, offer rematching/alternative",
        "user_inactivity": "NBA reminders, auto-archive after max inactivity",
        "sub_workflow_timeout": "Escalate to agent, manual intervention",
        "concurrent_modifications": "Optimistic locking on project version"
      },
      "implementation_priority": "P2",
      "implementation_wave": "Phase 2 — Operations",
      "human_decision_required": true,
      "human_decision_question": "Orchestrator implementation: workflow engine vs event-driven choreography",
      "status": "APPROVED"
    },
    {
      "extension_id": "EXT-WF-015",
      "source_concept": "Property Lifecycle (13 states)",
      "source_document": "LAWIM_UNIFIED_DOMAIN_MODEL.md §3 / PROPERTY_TYPE_CROSSWALK.md",
      "source_rule_ids": ["EXT-PROP-004"],
      "current_target": "Property model (V2)",
      "current_limitation": "V2 has 5 statuses (draft, open, closed, published, archived) — no enrichment or commercial pipeline",
      "extension_category": "workflow_extend_current",
      "proposed_domain": "Domain 2: Property/Listing Model",
      "proposed_entity": "Property",
      "proposed_structure": "EXTEND_CURRENT — Extend Property state machine from 5 to 13 states covering enrichment pipeline: reception → normalization → classification → validation → publication → matching → visit → negotiation → transaction → completion → archive/conserve/delete",
      "decision": "EXTEND_CURRENT",
      "workflow_id": "property_lifecycle",
      "entity_type": "Property",
      "initial_state": "creation",
      "states": ["creation", "normalization", "classification", "validation", "published", "matching", "visit", "negotiation", "transaction", "completed", "archived", "conserved", "deleted"],
      "terminal_states": ["completed", "archived", "conserved", "deleted"],
      "SLA": [
        {"state": "creation", "max_duration": "7d"},
        {"state": "normalization", "max_duration": "24h"},
        {"state": "classification", "max_duration": "24h"},
        {"state": "validation", "max_duration": "48h"},
        {"state": "published", "max_duration": "90d (auto-archive)"},
        {"state": "completed", "max_duration": "90d (auto-archive)"},
        {"state": "archived", "max_duration": "365d (auto-delete notification)"}
      ],
      "events": [
        "property.created (property_id, owner_id, family, type)",
        "property.normalized (property_id, normalization_result)",
        "property.classified (property_id, family, type, subtype)",
        "property.published (property_id, published_at, sie_code)",
        "property.matching_started (property_id)",
        "property.visit_scheduled (property_id, visit_id)",
        "property.negotiation_started (property_id)",
        "property.transaction_created (property_id, transaction_id)",
        "property.completed (property_id, outcome, price_final)",
        "property.archived (property_id, archive_reason)",
        "property.conserved (property_id, conserved_at)",
        "property.deleted (property_id, deleted_at)"
      ],
      "implementation_priority": "P1",
      "implementation_wave": "Phase 1 — Core Business",
      "human_decision_required": true,
      "human_decision_question": "State granularity: full 13-step or key additions",
      "status": "APPROVED"
    },
    {
      "extension_id": "EXT-WF-016",
      "source_concept": "Dossier Lifecycle (14 states)",
      "source_document": "LAWIM_UNIFIED_DOMAIN_MODEL.md §6 (Domain 5: Dossier/Project Model)",
      "source_rule_ids": [],
      "current_target": "Project model (V2)",
      "current_limitation": "V2 has Project with 5 statuses, no matching/consent logic",
      "extension_category": "workflow_extend_current",
      "proposed_domain": "Domain 5: Dossier/Project Model",
      "proposed_entity": "Project (as Dossier)",
      "proposed_structure": "EXTEND_CURRENT — Extend Project state machine from 5 to 14 states covering full dossier lifecycle: creation → qualification → matching → presentation → wait_demandeur → wait_holder → mise_en_relation → visit → negotiation → agreement → transaction → closure → archive → cancelled",
      "decision": "EXTEND_CURRENT",
      "workflow_id": "dossier_lifecycle",
      "entity_type": "Project",
      "initial_state": "creation",
      "states": ["creation", "qualification", "matching", "presentation", "wait_demandeur", "wait_holder", "mise_en_relation", "visit", "negotiation", "agreement", "transaction", "closure", "archive", "cancelled"],
      "terminal_states": ["closure", "archive", "cancelled"],
      "SLA": [
        {"state": "creation", "max_duration": "7d", "escalation": "Reminder to qualify"},
        {"state": "qualification", "max_duration": "30d", "escalation": "Reminder at 7d inactivity"},
        {"state": "wait_demandeur", "max_duration": "72h", "escalation": "Reminder at 24h, 48h"},
        {"state": "wait_holder", "max_duration": "72h", "escalation": "Reminder at 24h, 48h, 72h"},
        {"state": "mise_en_relation", "max_duration": "30d", "escalation": "Suggest visit"},
        {"state": "negotiation", "max_duration": "30d", "escalation": "Silence reminders at 48h, 96h, 168h, 240h"}
      ],
      "events": [
        "dossier.created (project_id, user_id, intent, project_type)",
        "dossier.qualification_completed (project_id, steps_completed)",
        "dossier.matches_presented (project_id, match_count, top_scores)",
        "dossier.demandeur_interested (project_id, property_id, timestamp)",
        "dossier.holder_favorable (project_id, holder_id, timestamp)",
        "dossier.contact_established (project_id, contact_id)",
        "dossier.visit_scheduled (project_id, visit_id)",
        "dossier.negotiation_started (project_id, negotiation_id)",
        "dossier.agreement_reached (project_id, terms_summary)",
        "dossier.transaction_initiated (project_id, transaction_id)",
        "dossier.closed (project_id, outcome, closed_at)",
        "dossier.archived (project_id, archive_reason)",
        "dossier.cancelled (project_id, reason)",
        "dossier.matching_failed (project_id, reason, suggestion)"
      ],
      "implementation_priority": "P1",
      "implementation_wave": "Phase 1 — Core Business",
      "human_decision_required": true,
      "human_decision_question": "Dossier state granularity: 14 states or simplified",
      "status": "APPROVED"
    },
    {
      "extension_id": "EXT-WF-017",
      "source_concept": "Negotiation Workflow (10 states)",
      "source_document": "LAWIM_UNIFIED_DOMAIN_MODEL.md §9 (Domain 8: Negotiation Workflow)",
      "source_rule_ids": [],
      "current_target": "Conversation model (V2) — negotiation stages",
      "current_limitation": "V2 has conversation_domain with basic negotiation stages (interest → negotiation → agreement → closed)",
      "extension_category": "workflow_enrich_current",
      "proposed_domain": "Domain 8: Negotiation Workflow",
      "proposed_entity": "Conversation (negotiation domain)",
      "proposed_structure": "ENRICH_CURRENT — Enrich current negotiation stages with offer/counter-offer tracking, negotiable elements per transaction type, silent-reminder system (48h/96h/168h/240h), and post-failure diagnostic",
      "decision": "ENRICH_CURRENT",
      "workflow_id": "negotiation_workflow",
      "entity_type": "Conversation",
      "initial_state": "not_started",
      "states": ["not_started", "demandeur_proposes", "holder_responds", "counter_offer", "accepted", "rejected", "silent", "failed", "escalated", "closed"],
      "terminal_states": ["accepted", "rejected", "failed", "closed"],
      "SLA": [
        {"period": "48h silence", "action": "First reminder"},
        {"period": "96h silence", "action": "Second reminder"},
        {"period": "168h (7d) silence", "action": "Final reminder"},
        {"period": "240h (10d) silence", "action": "Auto-close as failed (silence)"}
      ],
      "events": [
        "negotiation.started (negotiation_id, project_id, demandeur_id, holder_id)",
        "negotiation.offer_made (negotiation_id, offer_amount, offered_by, negotiable_elements)",
        "negotiation.counter_offer (negotiation_id, counter_amount, offered_by, terms)",
        "negotiation.accepted (negotiation_id, accepted_amount, accepted_by_both, accepted_at)",
        "negotiation.rejected (negotiation_id, rejected_by, reason)",
        "negotiation.silence_reminder (negotiation_id, reminder_number, days_silent)",
        "negotiation.escalated (negotiation_id, escalated_to, reason)",
        "negotiation.failed (negotiation_id, failure_reason, failure_diagnostic)",
        "negotiation.closed (negotiation_id, outcome, closed_at)"
      ],
      "failure_policy": {
        "silence_at_48h": "Send first reminder",
        "silence_at_96h": "Send second reminder with counter-offer prompt",
        "silence_at_168h": "Final reminder — will close",
        "silence_at_240h": "Auto-close as failed (silence)"
      },
      "implementation_priority": "P1",
      "implementation_wave": "Phase 1 — Core Business",
      "human_decision_required": false,
      "status": "APPROVED"
    },
    {
      "extension_id": "EXT-WF-018",
      "source_concept": "Qualification Workflow (10 steps)",
      "source_document": "LAWIM_UNIFIED_DOMAIN_MODEL.md §6.1.1 / EXT-QUAL-010",
      "source_rule_ids": ["EXT-QUAL-010"],
      "current_target": "Project model (V2)",
      "current_limitation": "V2 has flat journey steps with no progressive disclosure order",
      "extension_category": "workflow_generic_state_machine",
      "proposed_domain": "Domain 5: Dossier/Project Model (qualification sub-workflow)",
      "proposed_entity": "Project (qualification)",
      "proposed_structure": "CREATE_NEW_GENERIC_STATE_MACHINE — Implement ordered qualification wizard with 10-step progressive disclosure: Intention → Type → Ville → Quartier → Budget → Délai → Critères → Préférences → Confirmation → Escalade. Channel-adaptive (WhatsApp: 1 question, Telegram: 2-3, Dashboard: full).",
      "decision": "CREATE_NEW_GENERIC_STATE_MACHINE",
      "workflow_id": "qualification_workflow",
      "entity_type": "Project",
      "initial_state": "intention",
      "states": ["intention", "type", "ville", "quartier", "budget", "delai", "criteres", "preferences", "confirmation", "escalade", "completed"],
      "terminal_states": ["completed", "escalade"],
      "events": [
        "qualification.step_completed (project_id, step, step_number, data)",
        "qualification.completed (project_id, qualification_summary)",
        "qualification.escalated (project_id, reason, partial_data)",
        "qualification.corrected (project_id, step_reset, new_value)"
      ],
      "implementation_priority": "P1",
      "implementation_wave": "Phase 1 — Core Business",
      "human_decision_required": false,
      "status": "APPROVED"
    },
    {
      "extension_id": "EXT-WF-019",
      "source_concept": "Agent Onboarding (6 states)",
      "source_document": "LAWIM_UNIFIED_DOMAIN_MODEL.md §2 / EXT-RL-AGENCY-001",
      "source_rule_ids": ["EXT-RL-AGENCY-001"],
      "current_target": "User model (V2)",
      "current_limitation": "No structured agent onboarding workflow exists in V2",
      "extension_category": "workflow_enrich_current",
      "proposed_domain": "Domain 1: User/Role/Profile Model",
      "proposed_entity": "User (onboarding_status)",
      "proposed_structure": "ENRICH_CURRENT — Add onboarding_status field to User model with 6-state lifecycle: invited → account_created → phone_verified → cni_uploaded → validated → active. States stored as User.onboarding_status enum.",
      "decision": "ENRICH_CURRENT",
      "workflow_id": "agent_onboarding",
      "entity_type": "User",
      "initial_state": "invited",
      "states": ["invited", "account_created", "phone_verified", "cni_uploaded", "validated", "active", "rejected", "expired"],
      "terminal_states": ["active", "rejected", "expired"],
      "events": [
        "onboarding.invited (user_id, inviter_id, org_id, invitation_method)",
        "onboarding.account_created (user_id, created_at)",
        "onboarding.phone_verified (user_id, verified_at, method)",
        "onboarding.cni_uploaded (user_id, document_id, uploaded_at)",
        "onboarding.validated (user_id, validated_by, validated_at)",
        "onboarding.activated (user_id, agency_role, activated_at)",
        "onboarding.rejected (user_id, rejected_by, reason)",
        "onboarding.expired (user_id, expiry_reason)"
      ],
      "NBA_rules": [
        {"state": "invited", "nba": "Complete your registration"},
        {"state": "account_created", "nba": "Verify your phone number"},
        {"state": "phone_verified", "nba": "Upload your identity document"},
        {"state": "cni_uploaded", "nba": "Awaiting admin validation"},
        {"state": "validated", "nba": "Activate your agent account"},
        {"state": "active", "nba": "Welcome — complete your profile"},
        {"state": "rejected", "nba": "Review rejection reason and reapply"}
      ],
      "failure_policy": {
        "invitation_expires": "Allow inviter to resend (max 3)",
        "otp_verification_fails": "Allow retry (max 5), lock for 1h",
        "document_rejected": "Clear instructions, allow re-upload",
        "admin_not_validating": "Escalate after 7d to alternate admin"
      },
      "implementation_priority": "P2",
      "implementation_wave": "Phase 2 — Operations",
      "human_decision_required": true,
      "human_decision_question": "Onboarding step policy and validation requirements per step",
      "status": "APPROVED"
    },
    {
      "extension_id": "EXT-WF-020",
      "source_concept": "Organization Lifecycle (6 states)",
      "source_document": "LAWIM_UNIFIED_DOMAIN_MODEL.md §13 (Domain 12: Organization Model)",
      "source_rule_ids": ["EXT-RL-AGENCY-008"],
      "current_target": "Organization model (V2)",
      "current_limitation": "V2 Organization has users+properties but no agency-level trust, validations, or lifecycle states",
      "extension_category": "workflow_extend_current",
      "proposed_domain": "Domain 12: Organization Model",
      "proposed_entity": "Organization",
      "proposed_structure": "EXTEND_CURRENT — Add lifecycle_state enum to Organization model with 6-state lifecycle: creation → validation → active → suspended → dissolution → archived",
      "decision": "EXTEND_CURRENT",
      "workflow_id": "organization_lifecycle",
      "entity_type": "Organization",
      "initial_state": "creation",
      "states": ["creation", "validation", "active", "suspended", "dissolution", "archived"],
      "terminal_states": ["active", "archived"],
      "events": [
        "org.created (organization_id, responsible_id, name)",
        "org.validation_started (organization_id, admin_id)",
        "org.activated (organization_id, activated_at, verified_by)",
        "org.suspended (organization_id, reason, suspended_by)",
        "org.unsuspended (organization_id, resolved_by, restored_at)",
        "org.dissolution_started (organization_id, requested_by, reason)",
        "org.archived (organization_id, archived_at, archive_reason)"
      ],
      "NBA_rules": [
        {"state": "creation", "nba": "Complete agency registration — upload documents"},
        {"state": "validation", "nba": "Documents under review by LAWIM admin"},
        {"state": "active", "nba": "Agency is operational — manage agents"},
        {"state": "suspended", "nba": "Resolve suspension issue to restore"},
        {"state": "dissolution", "nba": "Complete dissolution — settle obligations"},
        {"state": "archived", "nba": "Agency closed — data preserved"}
      ],
      "failure_policy": {
        "registration_abandoned": "Auto-archive after 30d",
        "verification_incomplete": "Request additional docs, 7d deadline",
        "suspension_not_resolved": "Auto-transition to dissolution after 90d"
      },
      "implementation_priority": "P2",
      "implementation_wave": "Phase 2 — Operations",
      "human_decision_required": true,
      "human_decision_question": "Agency verification requirements and lifecycle enforcement",
      "status": "APPROVED"
    },
    {
      "extension_id": "EXT-WF-021",
      "source_concept": "Document Verification Workflow (6 states)",
      "source_document": "LAWIM_UNIFIED_DOMAIN_MODEL.md §15 (Domain 14: Document Model)",
      "source_rule_ids": [],
      "current_target": "No existing entity",
      "current_limitation": "No Document entity with type, verification, or lifecycle in V2",
      "extension_category": "workflow_specialized",
      "proposed_domain": "Domain 14: Document Model",
      "proposed_entity": "Document",
      "proposed_structure": "CREATE_SPECIALIZED_WORKFLOW — Implement Document entity with 6-state verification lifecycle: uploaded → pending → validated → rejected → expired → archived. Support per-transaction-type document requirements, admin validation workflow.",
      "decision": "CREATE_SPECIALIZED_WORKFLOW",
      "workflow_id": "document_verification",
      "entity_type": "Document",
      "initial_state": "uploaded",
      "states": ["uploaded", "pending", "validated", "rejected", "expired", "archived"],
      "terminal_states": ["validated", "rejected", "expired", "archived"],
      "SLA": [
        {"state": "pending", "max_duration": "7d", "escalation": "Escalate to alternate admin"},
        {"state": "validated", "max_duration": "Per document type", "escalation": "Notify 30d before expiry"},
        {"state": "expired", "max_duration": "90d", "escalation": "Auto-archive"},
        {"state": "rejected", "max_duration": "30d", "escalation": "Auto-archive"}
      ],
      "events": [
        "document.uploaded (document_id, document_type, uploaded_by, reference_entity)",
        "document.pending (document_id, queued_at)",
        "document.validated (document_id, validated_by, validated_at)",
        "document.rejected (document_id, rejected_by, reason)",
        "document.expired (document_id, expired_at, document_type)",
        "document.archived (document_id, archive_reason, archived_at)"
      ],
      "NBA_rules": [
        {"state": "uploaded", "nba": "Document queued for verification"},
        {"state": "pending", "nba": "Review document for verification (admin)"},
        {"state": "validated", "nba": "Document verified and active"},
        {"state": "rejected", "nba": "Review reason and upload corrected document"},
        {"state": "expired", "nba": "Upload new version of expired document"},
        {"state": "archived", "nba": "Document archived"}
      ],
      "failure_policy": {
        "admin_no_review_7d": "Escalate to alternate admin",
        "document_auto_rejected": "Virus/corrupt — notify uploader",
        "document_expiry": "Notify owner 30d before expiry",
        "new_version_uploaded": "Archive old version automatically"
      },
      "implementation_priority": "P2",
      "implementation_wave": "Phase 2 — Operations",
      "human_decision_required": false,
      "status": "APPROVED"
    }
  ],
  "decision_summary": {
    "description": "Decision distribution across all 21 workflows",
    "by_decision": {
      "EXTEND_CURRENT": {
        "count": 3,
        "workflows": ["Property Lifecycle", "Dossier Lifecycle", "Organization Lifecycle"]
      },
      "ENRICH_CURRENT": {
        "count": 2,
        "workflows": ["Negotiation Workflow", "Agent Onboarding"]
      },
      "CREATE_NEW_GENERIC_STATE_MACHINE": {
        "count": 5,
        "workflows": ["Matching Lifecycle", "Paid Services & Payment", "CRM Pipeline", "Main Cross-cutting", "Qualification Workflow"]
      },
      "CREATE_SPECIALIZED_WORKFLOW": {
        "count": 11,
        "workflows": ["Mise en Relation", "Visit Lifecycle", "Transaction Lifecycle", "Disputes & Incidents", "Mediation", "Publication SIE", "Redirection SIE", "Conversion & Attribution", "Agent Invitation", "Identity Resolution", "Document Verification"]
      }
    }
  },
  "phase_mapping": {
    "phase_1_core_business": {
      "workflows": ["EXT-WF-001", "EXT-WF-002", "EXT-WF-003", "EXT-WF-004", "EXT-WF-005", "EXT-WF-008", "EXT-WF-015", "EXT-WF-016", "EXT-WF-017", "EXT-WF-018"],
      "count": 10,
      "description": "Matching, Mise en Relation, Visit, Transaction, Paid Services, CRM Pipeline, Property Lifecycle, Dossier Lifecycle, Negotiation, Qualification"
    },
    "phase_2_operations": {
      "workflows": ["EXT-WF-006", "EXT-WF-012", "EXT-WF-014", "EXT-WF-019", "EXT-WF-020", "EXT-WF-021"],
      "count": 6,
      "description": "Disputes, Agent Invitation, Main Cross-cutting, Agent Onboarding, Organization Lifecycle, Document Verification"
    },
    "phase_3_analytics": {
      "workflows": ["EXT-WF-009", "EXT-WF-010", "EXT-WF-011"],
      "count": 3,
      "description": "Publication SIE, Redirection SIE, Conversion & Attribution"
    },
    "phase_4_enhancement": {
      "workflows": ["EXT-WF-007", "EXT-WF-013"],
      "count": 2,
      "description": "Mediation, Identity Resolution"
    }
  },
  "related_extensions": {
    "description": "Cross-references to other extension domains",
    "matching_engine": "EXT-MAT-* (5 scoring dimensions, 9 matching roles)",
    "qualification_matrices": "EXT-QUAL-* (107 matrices, 10-step progressive order)",
    "property_taxonomy": "EXT-PROP-* (7 families, property lifecycle integration)",
    "crm_scoring": "EXT-CRM-* (lead scoring, classification, routing)",
    "sla_breach_detection": "EXT-SLA-* (per-state SLA enforcement)",
    "nba_engine": "EXT-NBA-* (per-state next best actions)",
    "onboarding": "EXT-RL-AGENCY-001 (agent invitation onboarding)",
    "organization_lifecycle": "EXT-RL-AGENCY-008 (agency trust and validation)"
  }
}
